TOPSISKABIR/__init__.py
TOPSISKABIR/code.py
TOPSISKABIR-1.0.0.dist-info/METADATA
TOPSISKABIR-1.0.0.dist-info/WHEEL
TOPSISKABIR-1.0.0.dist-info/top_level.txt
TOPSISKABIR-1.0.0.dist-info/RECORD
