Metadata-Version: 2.1
Name: TOPSISKABIR
Version: 1.0.0
Summary: Topsis Calculation using weights and impacts
Home-page: UNKNOWN
Author: Kabir Chhabra
Author-email: <kabir12chhabra@gmail.com>
License: UNKNOWN
Keywords: python,topsis,topsis_rank,weights,impacts
Platform: UNKNOWN
Classifier: Development Status :: 1 - Planning
Classifier: Intended Audience :: Developers
Classifier: Programming Language :: Python :: 3
Classifier: Operating System :: Unix
Classifier: Operating System :: MacOS :: MacOS X
Classifier: Operating System :: Microsoft :: Windows
Requires-Dist: topsispy
Requires-Dist: numpy
Requires-Dist: pandas
